colab_easy_ui/ColabEasyUI.py
colab_easy_ui/ColabInternalFetcher.py
colab_easy_ui/EasyFileUploaderInternal.py
colab_easy_ui/Functions.py
colab_easy_ui/__init__.py
colab_easy_ui/beatrice_trainer_main.py
colab_easy_ui/const.py
colab_easy_ui/logger.py
colab_easy_ui/data/Response.py
colab_easy_ui/data/__init__.py
colab_easy_ui/frontend_beatrice_trainer_colab/dist/index.html
colab_easy_ui/frontend_beatrice_trainer_colab/dist/assets/index.js
colab_easy_ui/plugins/__init__.py
colab_easy_ui/plugins/json_save_function.py
colab_easy_ui/plugins/unzip_function.py
colab_easy_ui2-0.1.14.dist-info/METADATA
colab_easy_ui2-0.1.14.dist-info/WHEEL
colab_easy_ui2-0.1.14.dist-info/top_level.txt
colab_easy_ui2-0.1.14.dist-info/RECORD
